[
  {
    "ContainingType": "Introduction.Repository.Controllers.DogController",
    "Method": "PostDogSync",
    "RelativePath": "Dog/create",
    "HttpMethod": "POST",
    "IsController": true,
    "Order": 0,
    "Parameters": [
      {
        "Name": "dog",
        "Type": "Introduction.Model.Dog",
        "IsRequired": true
      }
    ],
    "ReturnTypes": []
  },
  {
    "ContainingType": "Introduction.Repository.Controllers.DogController",
    "Method": "DeleteDogSync",
    "RelativePath": "Dog/del",
    "HttpMethod": "DELETE",
    "IsController": true,
    "Order": 0,
    "Parameters": [
      {
        "Name": "id",
        "Type": "System.Guid",
        "IsRequired": false
      }
    ],
    "ReturnTypes": []
  },
  {
    "ContainingType": "Introduction.Repository.Controllers.DogController",
    "Method": "GetDogSync",
    "RelativePath": "Dog/get/{id}",
    "HttpMethod": "GET",
    "IsController": true,
    "Order": 0,
    "Parameters": [
      {
        "Name": "id",
        "Type": "System.Guid",
        "IsRequired": true
      }
    ],
    "ReturnTypes": []
  },
  {
    "ContainingType": "Introduction.Repository.Controllers.DogController",
    "Method": "GetAllSync",
    "RelativePath": "Dog/getall",
    "HttpMethod": "GET",
    "IsController": true,
    "Order": 0,
    "Parameters": [
      {
        "Name": "id",
        "Type": "System.Guid",
        "IsRequired": false
      },
      {
        "Name": "Name",
        "Type": "System.String",
        "IsRequired": false
      },
      {
        "Name": "isTrained",
        "Type": "System.Nullable\u00601[[System.Boolean, System.Private.CoreLib, Version=8.0.0.0, Culture=neutral, PublicKeyToken=7cec85d7bea7798e]]",
        "IsRequired": false
      },
      {
        "Name": "age",
        "Type": "System.Int32",
        "IsRequired": false
      },
      {
        "Name": "breed",
        "Type": "System.String",
        "IsRequired": false
      },
      {
        "Name": "orderby",
        "Type": "System.String",
        "IsRequired": false
      },
      {
        "Name": "sortDirection",
        "Type": "System.String",
        "IsRequired": false
      },
      {
        "Name": "pageSize",
        "Type": "System.Int32",
        "IsRequired": false
      },
      {
        "Name": "pageNumber",
        "Type": "System.Int32",
        "IsRequired": false
      }
    ],
    "ReturnTypes": []
  },
  {
    "ContainingType": "Introduction.Repository.Controllers.DogController",
    "Method": "UpdateDogSync",
    "RelativePath": "Dog/update/{id}",
    "HttpMethod": "PUT",
    "IsController": true,
    "Order": 0,
    "Parameters": [
      {
        "Name": "id",
        "Type": "System.Guid",
        "IsRequired": true
      }
    ],
    "ReturnTypes": []
  },
  {
    "ContainingType": "Introduction.Repository.Controllers.DogOwnerController",
    "Method": "PostDogOwnerSync",
    "RelativePath": "DogOwner/create",
    "HttpMethod": "POST",
    "IsController": true,
    "Order": 0,
    "Parameters": [
      {
        "Name": "dogOwner",
        "Type": "Introduction.Model.DogOwner",
        "IsRequired": true
      }
    ],
    "ReturnTypes": []
  },
  {
    "ContainingType": "Introduction.Repository.Controllers.DogOwnerController",
    "Method": "DeleteDogOwnerSync",
    "RelativePath": "DogOwner/del",
    "HttpMethod": "DELETE",
    "IsController": true,
    "Order": 0,
    "Parameters": [
      {
        "Name": "id",
        "Type": "System.Guid",
        "IsRequired": false
      },
      {
        "Name": "firstName",
        "Type": "System.String",
        "IsRequired": false
      }
    ],
    "ReturnTypes": []
  },
  {
    "ContainingType": "Introduction.Repository.Controllers.DogOwnerController",
    "Method": "GetDogOwnerSync",
    "RelativePath": "DogOwner/get/{id}",
    "HttpMethod": "GET",
    "IsController": true,
    "Order": 0,
    "Parameters": [
      {
        "Name": "id",
        "Type": "System.Guid",
        "IsRequired": true
      }
    ],
    "ReturnTypes": []
  },
  {
    "ContainingType": "Introduction.Repository.Controllers.DogOwnerController",
    "Method": "GetAllSync",
    "RelativePath": "DogOwner/getall",
    "HttpMethod": "GET",
    "IsController": true,
    "Order": 0,
    "Parameters": [
      {
        "Name": "Id",
        "Type": "System.Nullable\u00601[[System.Guid, System.Private.CoreLib, Version=8.0.0.0, Culture=neutral, PublicKeyToken=7cec85d7bea7798e]]",
        "IsRequired": false
      },
      {
        "Name": "firstName",
        "Type": "System.String",
        "IsRequired": false
      },
      {
        "Name": "lastName",
        "Type": "System.String",
        "IsRequired": false
      },
      {
        "Name": "phoneNumber",
        "Type": "System.String",
        "IsRequired": false
      },
      {
        "Name": "Email",
        "Type": "System.String",
        "IsRequired": false
      },
      {
        "Name": "orderBy",
        "Type": "System.String",
        "IsRequired": false
      },
      {
        "Name": "sortDirection",
        "Type": "System.String",
        "IsRequired": false
      },
      {
        "Name": "pageNumber",
        "Type": "System.Int32",
        "IsRequired": false
      },
      {
        "Name": "pageSize",
        "Type": "System.Int32",
        "IsRequired": false
      }
    ],
    "ReturnTypes": []
  },
  {
    "ContainingType": "Introduction.Repository.Controllers.DogOwnerController",
    "Method": "UpdateDogOwnerSync",
    "RelativePath": "DogOwner/update/{id}",
    "HttpMethod": "PUT",
    "IsController": true,
    "Order": 0,
    "Parameters": [
      {
        "Name": "id",
        "Type": "System.Guid",
        "IsRequired": true
      },
      {
        "Name": "dogOwner",
        "Type": "Introduction.Model.DogOwner",
        "IsRequired": true
      }
    ],
    "ReturnTypes": []
  },
  {
    "ContainingType": "Introduction.WebAPI.Controllers.AuthController",
    "Method": "Register",
    "RelativePath": "register",
    "HttpMethod": "POST",
    "IsController": true,
    "Order": 0,
    "Parameters": [
      {
        "Name": "user",
        "Type": "Introduction.Model.User",
        "IsRequired": true
      }
    ],
    "ReturnTypes": []
  },
  {
    "ContainingType": "Introduction.WebAPI.Controllers.AuthController",
    "Method": "Update",
    "RelativePath": "update/{id}",
    "HttpMethod": "PUT",
    "IsController": true,
    "Order": 0,
    "Parameters": [
      {
        "Name": "id",
        "Type": "System.Guid",
        "IsRequired": true
      },
      {
        "Name": "user",
        "Type": "Introduction.Model.User",
        "IsRequired": true
      }
    ],
    "ReturnTypes": []
  }
]